naja_atra/__init__.py
naja_atra/__main__.py
naja_atra/app_conf.py
naja_atra/models.py
naja_atra/server.py
naja_atra/http_servers/__init__.py
naja_atra/http_servers/coroutine_http_server.py
naja_atra/http_servers/http_server.py
naja_atra/http_servers/routing_server.py
naja_atra/http_servers/threading_http_server.py
naja_atra/request_handlers/__init__.py
naja_atra/request_handlers/http_controller_handler.py
naja_atra/request_handlers/http_request_handler.py
naja_atra/request_handlers/http_session_local_impl.py
naja_atra/request_handlers/model_bindings.py
naja_atra/request_handlers/websocket_controller_handler.py
naja_atra/utils/__init__.py
naja_atra/utils/http_utils.py
naja_atra/utils/logger.py
naja_atra-1.2.2.dist-info/licenses/LICENSE
naja_atra-1.2.2.dist-info/METADATA
naja_atra-1.2.2.dist-info/WHEEL
naja_atra-1.2.2.dist-info/top_level.txt
naja_atra-1.2.2.dist-info/RECORD
