Metadata-Version: 2.4
Name: naja-atra
Version: 1.2.2
Summary: This is a simple http server, use MVC like design.
Author-email: keijack <keijack.wu@gmail.com>
License-Expression: MIT
Project-URL: homepage, https://github.com/naja-atra/naja-atra
Project-URL: repository, https://github.com/naja-atra/naja-atra
Keywords: http-server,websocket,http,web,web-server
Classifier: Programming Language :: Python :: 3
Classifier: Operating System :: OS Independent
Requires-Python: >=3.7
License-File: LICENSE
Provides-Extra: test
Requires-Dist: websocket-client; extra == "test"
Requires-Dist: pytest; extra == "test"
Provides-Extra: dev
Requires-Dist: websocket-client; extra == "dev"
Dynamic: license-file
